hill_climbing/__init__.py
hill_climbing/climber.py
hill_climbing/utils.py
hill_climbing-0.1.8.dist-info/licenses/LICENSE
hill_climbing-0.1.8.dist-info/METADATA
hill_climbing-0.1.8.dist-info/WHEEL
hill_climbing-0.1.8.dist-info/top_level.txt
hill_climbing-0.1.8.dist-info/RECORD
