Metadata-Version: 2.4
Name: hill-climbing
Version: 0.1.8
Summary: A python package for ensembling machine learning predictions using hill climbing optimization
Author: Mahdi Ravaghi
Maintainer: Mahdi Ravaghi
License: Apache Software License 2.0
Project-URL: Homepage, https://github.com/ravaghi/hill-climbing
Project-URL: Bug Tracker, https://github.com/ravaghi/hill-climbing/issues
Project-URL: Documentation, https://github.com/ravaghi/hill-climbing#readme
Keywords: machine-learning,hill-climbing,optimization
Classifier: Intended Audience :: Science/Research
Classifier: Intended Audience :: Developers
Classifier: Programming Language :: Python :: 3
Classifier: Programming Language :: Python :: 3.7
Classifier: Programming Language :: Python :: 3.8
Classifier: Programming Language :: Python :: 3.9
Classifier: Programming Language :: Python :: 3.10
Classifier: Programming Language :: Python :: 3.11
Classifier: License :: OSI Approved :: Apache Software License
Classifier: Operating System :: OS Independent
Classifier: Topic :: Scientific/Engineering :: Artificial Intelligence
Classifier: Topic :: Scientific/Engineering :: Information Analysis
Requires-Python: >=3.7
License-File: LICENSE
Requires-Dist: numpy>=1.19.0
Requires-Dist: pandas>=1.0.0
Requires-Dist: scikit-learn>=0.24.0
Dynamic: license-file
